odoo/addons/l10n_ec_account_edi/README.rst
odoo/addons/l10n_ec_account_edi/__init__.py
odoo/addons/l10n_ec_account_edi/__manifest__.py
odoo/addons/l10n_ec_account_edi/data/cron_check_certificate.xml
odoo/addons/l10n_ec_account_edi/data/cron_check_unauthorized_electronic_document.xml
odoo/addons/l10n_ec_account_edi/data/cron_send_email_electronic_documents.xml
odoo/addons/l10n_ec_account_edi/data/edi_format_data.xml
odoo/addons/l10n_ec_account_edi/data/email_template_certificate_notify.xml
odoo/addons/l10n_ec_account_edi/data/email_template_edi_invoice.xml
odoo/addons/l10n_ec_account_edi/data/email_template_unauthorized_notify.xml
odoo/addons/l10n_ec_account_edi/data/edi_templates/edi_credit_note.xml
odoo/addons/l10n_ec_account_edi/data/edi_templates/edi_debit_note.xml
odoo/addons/l10n_ec_account_edi/data/edi_templates/edi_info_tributaria_data.xml
odoo/addons/l10n_ec_account_edi/data/edi_templates/edi_invoice.xml
odoo/addons/l10n_ec_account_edi/data/edi_templates/edi_liquidation.xml
odoo/addons/l10n_ec_account_edi/data/xsd/ComprobanteRetencion_V1.0.0.xsd
odoo/addons/l10n_ec_account_edi/data/xsd/ComprobanteRetencion_V2.0.0.xsd
odoo/addons/l10n_ec_account_edi/data/xsd/GuiaRemision_V1.0.0.xsd
odoo/addons/l10n_ec_account_edi/data/xsd/GuiaRemision_V1.1.0.xsd
odoo/addons/l10n_ec_account_edi/data/xsd/LiquidacionCompra_V1.0.0.xsd
odoo/addons/l10n_ec_account_edi/data/xsd/LiquidacionCompra_V1.1.0.xsd
odoo/addons/l10n_ec_account_edi/data/xsd/NotaCredito_V1.0.0.xsd
odoo/addons/l10n_ec_account_edi/data/xsd/NotaCredito_V1.1.0.xsd
odoo/addons/l10n_ec_account_edi/data/xsd/NotaDebito_V1.0.0.xsd
odoo/addons/l10n_ec_account_edi/data/xsd/factura_V1.0.0.xsd
odoo/addons/l10n_ec_account_edi/data/xsd/factura_V1.1.0.xsd
odoo/addons/l10n_ec_account_edi/data/xsd/factura_V2.0.0.xsd
odoo/addons/l10n_ec_account_edi/data/xsd/factura_V2.1.0.xsd
odoo/addons/l10n_ec_account_edi/i18n/es.po
odoo/addons/l10n_ec_account_edi/i18n/es_EC.po
odoo/addons/l10n_ec_account_edi/i18n/l10n_ec_account_edi.pot
odoo_addon_l10n_ec_account_edi-17.0.1.1.2.dist-info/METADATA
odoo_addon_l10n_ec_account_edi-17.0.1.1.2.dist-info/WHEEL
odoo_addon_l10n_ec_account_edi-17.0.1.1.2.dist-info/top_level.txt
odoo_addon_l10n_ec_account_edi-17.0.1.1.2.dist-info/RECORD
