Metadata-Version: 2.1
Name: odoo-addon-l10n_ec_account_edi
Version: 17.0.1.1.2
Requires-Python: >=3.10
Requires-Dist: cryptography==36.0.0
Requires-Dist: odoo-addon-l10n_ec_base>=17.0dev,<17.1dev
Requires-Dist: odoo>=17.0a,<17.1dev
Requires-Dist: xades==0.2.4
Requires-Dist: xmlsig==0.1.9
Requires-Dist: zeep
Summary: Electronic data interchange adapted Ecuadorian localization
Home-page: https://github.com/OCA/l10n-ecuador
License: AGPL-3
Author: Odoo Community Association (OCA), Carlos Lopez, Renan Nazate, Yazber Romero, Luis Romero, Jorge Quiguango
Author-email: support@odoo-community.org
Classifier: Programming Language :: Python
Classifier: Framework :: Odoo
Classifier: Framework :: Odoo :: 17.0
Classifier: License :: OSI Approved :: GNU Affero General Public License v3
